sddl/__main__.py
sddl-0.3.2.dist-info/METADATA
sddl-0.3.2.dist-info/WHEEL
sddl-0.3.2.dist-info/entry_points.txt
sddl-0.3.2.dist-info/RECORD
