Metadata-Version: 2.1
Name: sddl
Version: 0.3.2
Summary: CLI frontend for sddl-parser
Author: Max Harley
Author-email: maxh@maxh.io
Requires-Python: >=3.10,<4.0
Classifier: Programming Language :: Python :: 3
Classifier: Programming Language :: Python :: 3.10
Classifier: Programming Language :: Python :: 3.11
Classifier: Programming Language :: Python :: 3.12
Requires-Dist: sddl-parser (>=0.5.0,<0.6.0)
